dbplus/Database.py
dbplus/QueryStore.py
dbplus/Record.py
dbplus/RecordCollection.py
dbplus/Statement.py
dbplus/__init__.py
dbplus/helpers.py
dbplus/drivers/DB2.py
dbplus/drivers/MySQL.py
dbplus/drivers/Oracle.py
dbplus/drivers/Postgres.py
dbplus/drivers/SQLite.py
dbplus/drivers/__init__.py
dbplus-0.4.6.dist-info/licenses/license.txt
dbplus-0.4.6.dist-info/METADATA
dbplus-0.4.6.dist-info/WHEEL
dbplus-0.4.6.dist-info/top_level.txt
dbplus-0.4.6.dist-info/RECORD
