Metadata-Version: 2.4
Name: DBPlus
Version: 0.4.6
Summary: Database-agnostic SQL Interface for Postresql, MySQL, SQLite, DB2 and more
Home-page: https://github.com/klaasbrant/DBPlus
Author: Klaas Brant
Author-email: kbrant@kbce.com
License: ISC
License-File: license.txt
Dynamic: author
Dynamic: author-email
Dynamic: description
Dynamic: description-content-type
Dynamic: home-page
Dynamic: license
Dynamic: license-file
Dynamic: summary
